b3j0f/__init__.py
b3j0f/requester/__init__.py
b3j0f/requester/utils.py
b3j0f/requester/version.py
b3j0f/requester/driver/__init__.py
b3j0f/requester/driver/base.py
b3j0f/requester/driver/composite.py
b3j0f/requester/driver/ctx.py
b3j0f/requester/driver/custom.py
b3j0f/requester/driver/py.py
b3j0f/requester/driver/transaction.py
b3j0f/requester/driver/utils.py
b3j0f/requester/driver/test/__init__.py
b3j0f/requester/driver/test/base.py
b3j0f/requester/driver/test/composite.py
b3j0f/requester/driver/test/ctx.py
b3j0f/requester/driver/test/custom.py
b3j0f/requester/driver/test/py.py
b3j0f/requester/driver/test/transaction.py
b3j0f/requester/driver/test/utils.py
b3j0f/requester/request/__init__.py
b3j0f/requester/request/base.py
b3j0f/requester/request/consts.py
b3j0f/requester/request/expr.py
b3j0f/requester/request/crud/__init__.py
b3j0f/requester/request/crud/base.py
b3j0f/requester/request/crud/create.py
b3j0f/requester/request/crud/delete.py
b3j0f/requester/request/crud/join.py
b3j0f/requester/request/crud/read.py
b3j0f/requester/request/crud/update.py
b3j0f/requester/request/crud/test/__init__.py
b3j0f/requester/request/crud/test/base.py
b3j0f/requester/request/crud/test/create.py
b3j0f/requester/request/crud/test/delete.py
b3j0f/requester/request/crud/test/read.py
b3j0f/requester/request/crud/test/update.py
b3j0f/requester/request/test/__init__.py
b3j0f/requester/request/test/base.py
b3j0f/requester/request/test/consts.py
b3j0f/requester/request/test/expr.py
b3j0f/requester/test/__init__.py
b3j0f/requester/test/utils.py
b3j0f.requester-0.0.4.dist-info/DESCRIPTION.rst
b3j0f.requester-0.0.4.dist-info/METADATA
b3j0f.requester-0.0.4.dist-info/RECORD
b3j0f.requester-0.0.4.dist-info/WHEEL
b3j0f.requester-0.0.4.dist-info/metadata.json
b3j0f.requester-0.0.4.dist-info/top_level.txt
