Metadata-Version: 2.0
Name: b3j0f.requester
Version: 0.0.4
Summary: Python abstract data request library.
Home-page: https://github.com/b3j0f/requester
Author: b3j0f
Author-email: ib3j0f@gmail.com
License: MIT License
Keywords: requester,query,system,access,data,crud,create,delete,update,read,run,distributed,request
Platform: UNKNOWN
Classifier: Development Status :: 4 - Beta
Classifier: License :: OSI Approved :: MIT License
Classifier: Natural Language :: French
Classifier: Operating System :: OS Independent
Classifier: Topic :: Utilities
Classifier: Topic :: Software Development
Classifier: Intended Audience :: Developers
Classifier: Programming Language :: Python
Classifier: Programming Language :: Python :: 2.6
Classifier: Programming Language :: Python :: 2.7
Classifier: Programming Language :: Python :: 3
Classifier: Programming Language :: Python :: 3.0
Classifier: Programming Language :: Python :: 3.1
Classifier: Programming Language :: Python :: 3.2
Classifier: Programming Language :: Python :: 3.3
Classifier: Programming Language :: Python :: 3.4
Classifier: Programming Language :: Python :: 3.5
Classifier: Programming Language :: Python :: Implementation :: CPython
Requires-Dist: b3j0f.utils
Requires-Dist: b3j0f.annotation
Requires-Dist: b3j0f.schema
Requires-Dist: six
Requires-Dist: enum34
Requires-Dist: soundex
